pyconafrica/__init__.py
pyconafrica/ghana19/__init__.py
pyconafrica/ghana19/conduct.py
pyconafrica/ghana19/gfx.py
pyconafrica/ghana19/schedule.py
pyconafrica/ghana19/sponsors.py
pyconafrica/ghana19/team.py
pyconafrica_info-0.1.0.dist-info/LICENSE.txt
pyconafrica_info-0.1.0.dist-info/METADATA
pyconafrica_info-0.1.0.dist-info/WHEEL
pyconafrica_info-0.1.0.dist-info/top_level.txt
pyconafrica_info-0.1.0.dist-info/RECORD
