Metadata-Version: 2.1
Name: pyconafrica-info
Version: 0.1.0
Summary: PyCON Africa library to get all informations related to the yearly events.
Home-page: https://github.com/jefcolbi/pyconafrica
Author: jefcolbi
Author-email: jefcolbi@gmail.com
License: MIT
Platform: UNKNOWN
Classifier: Natural Language :: English
Classifier: Natural Language :: French
Classifier: Development Status :: 5 - Production/Stable
Classifier: Programming Language :: Python
Classifier: Programming Language :: Python :: 3.6
Classifier: License :: OSI Approved :: GNU General Public License v3 or later (GPLv3+)
Requires-Python: >=2
Requires-Dist: colorama
